{
  "slug": "projetos-educacionais-inclusao",
  "title": "Projetos Educacionais e de Inclusão do Instituto Mãos de Ouro",
  "description": "Descubra como os projetos educacionais do Instituto transformam vidas e promovem a inclusão social.",
  "image": "/assets/contents/blog/projetos-educacionais-inclusao/0.jpg",
  "fullDescription": "O Instituto Mãos de Ouro desenvolve uma série de projetos que visam à educação inclusiva, oferecendo cursos de LIBRAS, oficinas culturais e atividades lúdicas. Essas iniciativas não só ampliam o acesso ao conhecimento para a comunidade surda, mas também fortalecem a autoestima e promovem a integração entre surdos e ouvintes. Por meio desses projetos, a instituição tem contribuído para a formação de uma rede de apoio que transforma a realidade educacional em diversas cidades do Marajó.",
  "color": "bg-primary",
  "date": "Junho de 2019",
  "location": "Diversas cidades do Marajó",
  "videos": [
    ["https://www.youtube-nocookie.com/embed/fKCDqwHJbIE?rel=0",1],
    ["https://www.youtube-nocookie.com/embed/_NecYwiabj8?rel=0",2],
    ["https://www.youtube-nocookie.com/embed/SoQTpUujOe4?rel=0",3],
    ["https://www.youtube-nocookie.com/embed/WQ10I3x5teY?rel=0",4],
    ["https://www.youtube-nocookie.com/embed/JaVPPX4Z37I?rel=0",5]
  ],
  "gallery": [],
  "objectives": [
    "Oferecer cursos de LIBRAS para todas as idades",
    "Capacitar profissionais para a inclusão de surdos",
    "Criar ambientes de aprendizagem colaborativa",
    "Fomentar a integração entre surdos e ouvintes"
  ],
  "impact": "Centenas de alunos já passaram por nossos cursos, promovendo transformações significativas e gerando uma maior integração social em comunidades espalhadas por diversas cidades."
}
